docparser_feb/__init__.py
docparser_feb/api/__init__.py
docparser_feb/api/functional/__init__.py
docparser_feb/api/functional/html_parser.py
docparser_feb/api/functional/pdf_parser.py
docparser_feb/api/server/settings.py
docparser_feb/scripts/__init__.py
docparser_feb/scripts/file_utils.py
docparser_feb/scripts/log_level.py
docparser_feb/scripts/markdown.py
docparser_feb/scripts/string_utils.py
docparser_feb/scripts/nlp/__init__.py
docparser_feb/scripts/nlp/query.py
docparser_feb/scripts/nlp/rag_tokenizer.py
docparser_feb/scripts/nlp/split_text.py
docparser_feb/scripts/nlp/surname.py
docparser_feb/scripts/nlp/synonym.py
docparser_feb/scripts/nlp/term_weight.py
docparser_feb/scripts/openai/openai.py
docparser_feb/scripts/openai/prompts.py
docparser_feb/scripts/postprocess/__init__.py
docparser_feb/scripts/postprocess/html_postprocess.py
docparser_feb/scripts/postprocess/pdf_postprocess.py
docparser_feb/scripts/rendering/pdf_rendering.py
docparser_feb/src/__init__.py
docparser_feb/src/parser/__init__.py
docparser_feb/src/parser/docx_parser.py
docparser_feb/src/parser/excel_parser.py
docparser_feb/src/parser/html_parser.py
docparser_feb/src/parser/pdf_parser.py
docparser_feb/src/parser/resume/__init__.py
docparser_feb/src/parser/resume/step_one.py
docparser_feb/src/parser/resume/step_two.py
docparser_feb/src/parser/resume/entities/__init__.py
docparser_feb/src/parser/resume/entities/corporations.py
docparser_feb/src/parser/resume/entities/degrees.py
docparser_feb/src/parser/resume/entities/industries.py
docparser_feb/src/parser/resume/entities/regions.py
docparser_feb/src/parser/resume/entities/schools.py
docparser_feb/src/parser/resume/entities/res/corp.tks.freq.json
docparser_feb/src/parser/resume/entities/res/corp_baike_len.csv
docparser_feb/src/parser/resume/entities/res/corp_tag.json
docparser_feb/src/parser/resume/entities/res/good_corp.json
docparser_feb/src/parser/resume/entities/res/good_sch.json
docparser_feb/src/parser/resume/entities/res/school.rank.csv
docparser_feb-0.1.5.dist-info/LICENSE
docparser_feb-0.1.5.dist-info/METADATA
docparser_feb-0.1.5.dist-info/WHEEL
docparser_feb-0.1.5.dist-info/entry_points.txt
docparser_feb-0.1.5.dist-info/top_level.txt
docparser_feb-0.1.5.dist-info/RECORD
