Metadata-Version: 2.1
Name: docparser-feb
Version: 0.1.5
Summary: Document parsing tool for LLM training and Rag
Author-email: Licheng Wang <244267620@qq.com>
License: MIT
Project-URL: Homepage, https://github.com/feb-co/DocParser
Keywords: pdf,LLM,ChatGPT,transformer,pytorch,deep learning
Classifier: Development Status :: 4 - Beta
Classifier: Intended Audience :: Developers
Classifier: Intended Audience :: Education
Classifier: Intended Audience :: Science/Research
Classifier: License :: OSI Approved :: MIT License
Classifier: Operating System :: OS Independent
Classifier: Programming Language :: Python :: 3
Classifier: Programming Language :: Python :: 3.8
Classifier: Programming Language :: Python :: 3.9
Classifier: Programming Language :: Python :: 3.10
Classifier: Programming Language :: Python :: 3.11
Classifier: Topic :: Scientific/Engineering :: Artificial Intelligence
Requires-Python: >=3.8
License-File: LICENSE
Requires-Dist: albumentations
Requires-Dist: bs4
Requires-Dist: cn2an
Requires-Dist: cachetools
Requires-Dist: datrie
Requires-Dist: effdet
Requires-Dist: hanziconv
Requires-Dist: html-text
Requires-Dist: lxml
Requires-Dist: layoutparser
Requires-Dist: nougat-ocr
Requires-Dist: nltk
Requires-Dist: opencv-python
Requires-Dist: openpyxl
Requires-Dist: onnxruntime
Requires-Dist: pdfplumber
Requires-Dist: pyclipper
Requires-Dist: PyPDF2
Requires-Dist: python-docx
Requires-Dist: python-pptx
Requires-Dist: ruamel.yaml
Requires-Dist: roman-numbers
Requires-Dist: shapely
Requires-Dist: StrEnum
Requires-Dist: tika
Requires-Dist: tiktoken
Requires-Dist: transformers
Requires-Dist: tokenizers
Requires-Dist: word2number
Requires-Dist: xgboost
Requires-Dist: langdetect
